{
    "excludeFiles": [
        "debian/**",
        "libs/**",
        "node_modules/**",
        "configs/current/**",
        ".enb/tmp/**",
        "src/*.bundles/**",
        "src/blocks/*.blocks/*/*.i18n",
        "src/blocks/*.blocks/*/*.deps.js",
        "src/blocks/*.blocks/*/*/*.deps.js",
        "src/blocks/*.blocks/*/*/*/*.deps.js"
    ],
    "requireCurlyBraces": [
        "if",
        "else",
        "for",
        "while",
        "do",
        "try",
        "catch",
        "case",
        "default"
    ],
    "requireSpaceAfterKeywords": [
        "if",
        "else",
        "for",
        "while",
        "do",
        "switch",
        "return",
        "try",
        "catch"
    ],
    "disallowKeywords": [
        "with"
    ],
    "disallowKeywordsOnNewLine": [
        "else",
        "catch"
    ],
    "requireParenthesesAroundIIFE": true,
    "requireSpacesInFunctionExpression": {
        "beforeOpeningCurlyBrace": true
    },
    "disallowSpacesInFunctionExpression": {
        "beforeOpeningRoundBrace": true
    },
    "requireMultipleVarDecl": true,
    "disallowEmptyBlocks": true,
    "requireSpacesInsideObjectBrackets": "all",
    "disallowSpacesInsideParentheses": true,
    "disallowSpaceAfterObjectKeys": true,
    "disallowQuotedKeysInObjects": "allButReserved",
    "requireCommaBeforeLineBreak": true,
    "disallowYodaConditions": true,
    "disallowLeftStickedOperators": [
        "?"
    ],
    "disallowRightStickedOperators": [
        "?",
        ":"
    ],
    "requireLeftStickedOperators": [
        ","
    ],
    "disallowSpaceAfterPrefixUnaryOperators": [
        "++",
        "--",
        "+",
        "-",
        "~",
        "!"
    ],
    "disallowSpaceBeforePostfixUnaryOperators": [
        "++",
        "--"
    ],
    "requireSpaceBeforeBinaryOperators": [
        "+",
        "-",
        "/",
        "*",
        "=",
        "==",
        "===",
        "!=",
        "!==",
        ">",
        ">=",
        "<",
        "<="
    ],
    "requireSpaceAfterBinaryOperators": [
        "+",
        "-",
        "/",
        "*",
        "=",
        "==",
        "===",
        "!=",
        "!==",
        ">",
        ">=",
        "<",
        "<="
    ],
    "disallowImplicitTypeConversion": [
        "boolean",
        "string",
        "numeric",
        "binary"
    ],
    "safeContextKeyword": "_this",
    "requireDotNotation": true,
    "maximumLineLength": 120,
    "validateQuoteMarks": "'",
    "disallowMultipleLineBreaks": true,
    "validateLineBreaks": "LF",
    "disallowMultipleLineStrings": true,
    "disallowMixedSpacesAndTabs": true,
    "disallowTrailingWhitespace": true,
    "requireCapitalizedConstructors": true,
    "requireLineFeedAtFileEnd": true,
    "validateJSDoc": {
        "checkParamNames": true,
        "checkRedundantParams": true,
        "requireParamTypes": true
    }
}